lvfpgahdltools/__init__.py
lvfpgahdltools/__main__.py
lvfpgahdltools/common.py
lvfpgahdltools/createlvbitfile.py
lvfpgahdltools/createvivadoproject.py
lvfpgahdltools/extractdependencies.py
lvfpgahdltools/genlvtargetsupport.py
lvfpgahdltools/getwindownetlist.py
lvfpgahdltools/installlvtargetsupport.py
lvfpgahdltools/launchvivado.py
lvfpgahdltools/migrateclip.py
lvfpgahdltools-0.0.13.dist-info/LICENSE
lvfpgahdltools-0.0.13.dist-info/METADATA
lvfpgahdltools-0.0.13.dist-info/WHEEL
lvfpgahdltools-0.0.13.dist-info/entry_points.txt
lvfpgahdltools-0.0.13.dist-info/RECORD
